fontools/__init__.py
fontools/bed.py
fontools/ensembl.py
fontools/ensembl_db.py
fontools/gff.py
fontools/indexes.py
fontools/naming.py
fontools/remote.py
fontools/utils.py
fontools-0.8.0.dist-info/licenses/LICENSE
fontools_scripts/__init__.py
fontools_scripts/ensembl2ucsc.py
fontools_scripts/fasta_format.py
fontools_scripts/fasta_seq_length.py
fontools_scripts/fon_import.py
fontools_scripts/fon_mask_fasta.py
fontools_scripts/fon_transform.py
fontools_scripts/import_ensembl.py
fontools_scripts/merge_annot.py
fontools-0.8.0.dist-info/METADATA
fontools-0.8.0.dist-info/WHEEL
fontools-0.8.0.dist-info/entry_points.txt
fontools-0.8.0.dist-info/top_level.txt
fontools-0.8.0.dist-info/RECORD
