Metadata-Version: 2.4
Name: FONtools
Version: 0.8.0
Summary: JSON-based FON (Feature Object Notation) format and tools to simplify genomic annotations usage
Author: Charles E. Vejnar
License-Expression: MPL-2.0
Project-URL: homepage, https://git.sr.ht/~vejnar/FONtools
Classifier: Programming Language :: Python :: 3
Classifier: Topic :: Scientific/Engineering :: Bio-Informatics
Requires-Python: >=3.9
License-File: LICENSE
Requires-Dist: pyfaidx
Requires-Dist: pyfnutils
Requires-Dist: zstandard
Dynamic: license-file
